pytrition/main.py
pytrition-0.1.0.dist-info/LICENSE
pytrition-0.1.0.dist-info/METADATA
pytrition-0.1.0.dist-info/WHEEL
pytrition-0.1.0.dist-info/RECORD
